chrometrace/__init__.py
chrometrace/chrometrace.py
chrometrace/py.typed
chrometrace-0.2.1.dist-info/METADATA
chrometrace-0.2.1.dist-info/WHEEL
chrometrace-0.2.1.dist-info/licenses/LICENSE
chrometrace-0.2.1.dist-info/RECORD
