Metadata-Version: 2.4
Name: chrometrace
Version: 0.2.1
Summary: A Python library for Chrome Trace Viewer files
Project-URL: Homepage, https://github.com/jonasehrlich/chrometrace
Project-URL: Repository, https://github.com/jonasehrlich/chrometrace
Author-email: Jonas Ehrlich <jonas.ehrlich@gmail.com>
License-Expression: MIT
License-File: LICENSE
Keywords: chromium,trace
Requires-Python: >=3.11
